augmixations/__init__.py
augmixations/configs.py
augmixations/core.py
augmixations/cutmix.py
augmixations/cutout.py
augmixations/mixin.py
augmixations/mixup.py
augmixations/utils.py
settings/__init__.py
tests/__init__.py
tests/conftest.py
tests/test_core.py
tests/test_cutmix.py
tests/test_cutout.py
tests/test_mixin.py
tests/test_mixup.py
tests/test_utils.py
augmixations-0.2.21.dist-info/LICENSE
augmixations-0.2.21.dist-info/METADATA
augmixations-0.2.21.dist-info/WHEEL
augmixations-0.2.21.dist-info/top_level.txt
augmixations-0.2.21.dist-info/RECORD
