Metadata-Version: 2.1
Name: augmixations
Version: 0.2.21
Summary: Object detection augmentations.
Home-page: https://github.com/TheDenk/augmixations
Author: Karachev Denis
Author-email: komedian@bk.ru
License: MIT
Platform: UNKNOWN
Requires-Dist: numpy (>=1.11.1)
